pg_query.cpython-311-aarch64-linux-gnu.so
psqlparse2/__init__.py
psqlparse2/__init__.pyi
psqlparse2/py.typed
psqlparse2/pb/pg_query_pb2.py
psqlparse2/pb/__init__.py
psqlparse2/pb/pg_query_pb2.pyi
psqlparse2-0.0.17.dist-info/top_level.txt
psqlparse2-0.0.17.dist-info/RECORD
psqlparse2-0.0.17.dist-info/LICENSE
psqlparse2-0.0.17.dist-info/METADATA
psqlparse2-0.0.17.dist-info/WHEEL
