Metadata-Version: 2.1
Name: psqlparse2
Version: 0.0.17
Summary: libpg_query wrapper for Python
Author-email: Dani Maarouf <dmaarouf@cisco.com>
License: Copyright (c) 2024, Dani Maarouf
Project-URL: Repository, https://github.com/dani-maarouf/psqlparse2
Keywords: database,postgres,sql,parser,libpg_query,pg_query
Classifier: Development Status :: 3 - Alpha
Classifier: Intended Audience :: Developers
Classifier: License :: OSI Approved :: BSD License
Classifier: Operating System :: POSIX
Classifier: Programming Language :: Python :: 3 :: Only
Classifier: Programming Language :: Python :: 3.8
Classifier: Programming Language :: Python :: 3.9
Classifier: Programming Language :: Python :: 3.10
Classifier: Programming Language :: Python :: 3.11
Classifier: Programming Language :: Python :: 3.12
Classifier: Programming Language :: SQL
Classifier: Topic :: Database :: Front-Ends
Requires-Python: >=3.8.0
License-File: LICENSE
Requires-Dist: protobuf<6.0,>=5.26.1
Requires-Dist: types-protobuf<6.0,>=5.26.1
Provides-Extra: dev
Requires-Dist: black>=24.4.2; extra == "dev"
Requires-Dist: ruff>=0.4.4; extra == "dev"
Requires-Dist: mypy>=1.10.0; extra == "dev"
Requires-Dist: pytest<9,>=8.2; extra == "dev"
Requires-Dist: pytest-cov<6,>=5.0.0; extra == "dev"
Requires-Dist: grpcio-tools<1.70,>=1.60.0; extra == "dev"
